first_package/Area_Fig.py
first_package/__init__.py
AreaOfFig24test-0.0.2.dist-info/LICENSE
AreaOfFig24test-0.0.2.dist-info/METADATA
AreaOfFig24test-0.0.2.dist-info/WHEEL
AreaOfFig24test-0.0.2.dist-info/top_level.txt
AreaOfFig24test-0.0.2.dist-info/RECORD
